{
  "legacy": {
    "description": "Fixed to v4.3.9",
    "hide": false,
    "last_updated": "2024-02-26T10:29:36.000Z",
    "last_updated_url": "https://github.com/hotio/qbittorrent/actions/runs/8047352523",
    "latest": false,
    "tags": [
      "legacy",
      "legacy-4.3.9",
      "legacy-2a21bcd"
    ]
  },
  "release": {
    "description": "Releases",
    "hide": false,
    "last_updated": "2024-02-26T21:31:17.000Z",
    "last_updated_url": "https://github.com/hotio/qbittorrent/actions/runs/8055713747",
    "latest": true,
    "tags": [
      "release",
      "release-4.6.3",
      "release-b5caaab"
    ]
  }
}
