{
  "legacy": {
    "description": "Fixed to v4.3.9",
    "hide": false,
    "last_updated": "2025-04-15T12:30:57.000Z",
    "last_updated_url": "https://github.com/hotio/qbittorrent/actions/runs/14469214940",
    "latest": false,
    "tags": [
      "legacy",
      "legacy-4.3.9",
      "legacy-f5015a4"
    ]
  },
  "release": {
    "description": "Releases",
    "hide": false,
    "last_updated": "2025-04-13T22:11:56.000Z",
    "last_updated_url": "https://github.com/hotio/qbittorrent/actions/runs/14433802391",
    "latest": true,
    "tags": [
      "release",
      "release-5.0.5",
      "release-e0f226c"
    ]
  }
}
